lazr.sshserver-0.1.14-py3.13-nspkg.pth
lazr/sshserver/README.txt
lazr/sshserver/__init__.py
lazr/sshserver/accesslog.py
lazr/sshserver/auth.py
lazr/sshserver/events.py
lazr/sshserver/service.py
lazr/sshserver/session.py
lazr/sshserver/sftp.py
lazr/sshserver/docs/__init__.py
lazr/sshserver/tests/__init__.py
lazr/sshserver/tests/test_accesslog.py
lazr/sshserver/tests/test_auth.py
lazr/sshserver/tests/test_docs.py
lazr/sshserver/tests/test_events.py
lazr/sshserver/tests/test_session.py
lazr/sshserver/tests/keys/ssh_host_key_rsa
lazr/sshserver/tests/keys/ssh_host_key_rsa.pub
lazr.sshserver-0.1.14.dist-info/COPYING.txt
lazr.sshserver-0.1.14.dist-info/METADATA
lazr.sshserver-0.1.14.dist-info/WHEEL
lazr.sshserver-0.1.14.dist-info/namespace_packages.txt
lazr.sshserver-0.1.14.dist-info/top_level.txt
lazr.sshserver-0.1.14.dist-info/RECORD
