Metadata-Version: 2.1
Name: lazr.sshserver
Version: 0.1.14
Summary: The Launchpad SSH server.
Home-page: https://launchpad.net/lazr.sshserver
Download-URL: https://launchpad.net/lazr.sshserver/+download
Maintainer: LAZR Developers
Maintainer-email: lazr-developers@lists.launchpad.net
License: LGPL v3
Project-URL: Source, https://code.launchpad.net/lazr.sshserver
Project-URL: Issue Tracker, https://bugs.launchpad.net/lazr.sshserver
Classifier: Development Status :: 5 - Production/Stable
Classifier: Intended Audience :: Developers
Classifier: License :: OSI Approved :: GNU Library or Lesser General Public License (LGPL)
Classifier: Operating System :: OS Independent
Classifier: Programming Language :: Python
Classifier: Programming Language :: Python :: 3
Classifier: Programming Language :: Python :: 3.8
Classifier: Programming Language :: Python :: 3.9
Classifier: Programming Language :: Python :: 3.10
Classifier: Programming Language :: Python :: 3.11
Classifier: Programming Language :: Python :: 3.12
Classifier: Programming Language :: Python :: 3.13
Requires-Python: >=3.8
License-File: COPYING.txt
Requires-Dist: setuptools
Requires-Dist: Twisted[conch]>=16.2.0
Requires-Dist: zope.component
Requires-Dist: zope.event
Requires-Dist: zope.interface
Provides-Extra: docs
Requires-Dist: Sphinx; extra == "docs"
Provides-Extra: test
Requires-Dist: breezy; extra == "test"
Requires-Dist: fixtures; extra == "test"
Requires-Dist: flake8; extra == "test"
Requires-Dist: testtools; extra == "test"
Requires-Dist: zope.testrunner; extra == "test"
